satellite_tle/__init__.py
satellite_tle/fetch_tle.py
satellite_tle/fetch_tles.py
satellite_tle/sources.csv
satellitetle-0.18.0.dist-info/licenses/AUTHORS
satellitetle-0.18.0.dist-info/licenses/LICENSE.txt
satellitetle-0.18.0.dist-info/METADATA
satellitetle-0.18.0.dist-info/WHEEL
satellitetle-0.18.0.dist-info/top_level.txt
satellitetle-0.18.0.dist-info/RECORD
