Metadata-Version: 2.4
Name: satellitetle
Version: 0.18.0
Summary: Fetch satellite TLEs from various online sources
Home-page: https://gitlab.com/librespacefoundation/python-satellitetle
Author: Fabian P. Schmidt
Author-email: kerel-fs@gmx.de
License: MIT
Classifier: Programming Language :: Python :: 3
License-File: LICENSE.txt
License-File: AUTHORS
Requires-Dist: requests
Requires-Dist: sgp4~=2.25
Requires-Dist: spacetrack~=1.4.0
Requires-Dist: importlib-metadata; python_version < "3.13"
Provides-Extra: dev
Requires-Dist: flake8~=3.9.0; extra == "dev"
Requires-Dist: tox~=4.12.1; extra == "dev"
Dynamic: license-file
